snifter/__init__.py
snifter/main.py
snifter-0.0.19.dist-info/LICENSE.txt
snifter-0.0.19.dist-info/METADATA
snifter-0.0.19.dist-info/WHEEL
snifter-0.0.19.dist-info/entry_points.txt
snifter-0.0.19.dist-info/top_level.txt
snifter-0.0.19.dist-info/RECORD
