Metadata-Version: 2.1
Name: snifter
Version: 0.0.19
Summary: Listen to and inspect AWS SNS topic data
Home-page: https://github.com/pyscaffold/pyscaffold/
Author: Ashton Honnecke
Author-email: ashton@pixelstub.com
License: MIT
Project-URL: Source, https://github.com/ahonnecke/snifter/
Platform: any
Classifier: Development Status :: 4 - Beta
Classifier: Programming Language :: Python
License-File: LICENSE.txt
Requires-Dist: argparse
Requires-Dist: boto3
Requires-Dist: botocore
Requires-Dist: importlib-metadata ; python_version < "3.8"
Provides-Extra: testing
Requires-Dist: setuptools ; extra == 'testing'
Requires-Dist: pytest ; extra == 'testing'
Requires-Dist: pytest-cov ; extra == 'testing'
